mozilla_django_oidc/__init__.py
mozilla_django_oidc/auth.py
mozilla_django_oidc/middleware.py
mozilla_django_oidc/urls.py
mozilla_django_oidc/utils.py
mozilla_django_oidc/views.py
mozilla_django_oidc/contrib/__init__.py
mozilla_django_oidc/contrib/drf.py
mozilla_django_oidc-5.0.2.dist-info/licenses/AUTHORS.rst
mozilla_django_oidc-5.0.2.dist-info/licenses/LICENSE
mozilla_django_oidc-5.0.2.dist-info/METADATA
mozilla_django_oidc-5.0.2.dist-info/WHEEL
mozilla_django_oidc-5.0.2.dist-info/top_level.txt
mozilla_django_oidc-5.0.2.dist-info/RECORD
